WKTUtils/FilesToWKT.py
WKTUtils/Input.py
WKTUtils/RepairWKT.py
WKTUtils/ValidateWKT.py
WKTUtils/__init__.py
WKTUtils/asf_env.py
WKTUtils-2.0.0.dist-info/LICENSE
WKTUtils-2.0.0.dist-info/METADATA
WKTUtils-2.0.0.dist-info/WHEEL
WKTUtils-2.0.0.dist-info/top_level.txt
WKTUtils-2.0.0.dist-info/RECORD
