Metadata-Version: 2.1
Name: WKTUtils
Version: 2.0.0
Summary: A few WKT utilities for use elsewhere
Home-page: https://github.com/asfadmin/Discovery-WKTUtils.git
Author: ASF Discovery Team
Author-email: uaf-asf-discovery@alaska.edu
Classifier: Programming Language :: Python :: 3
Classifier: License :: OSI Approved :: BSD License
Classifier: Operating System :: OS Independent
Requires-Python: >=3.8
License-File: LICENSE
Requires-Dist: dateparser
Requires-Dist: defusedxml
Requires-Dist: geomet
Requires-Dist: geopandas
Requires-Dist: kml2geojson
Requires-Dist: pyshp
Requires-Dist: PyYAML
Requires-Dist: Shapely
Provides-Extra: extras
Requires-Dist: requests ; extra == 'extras'
Requires-Dist: scikit-learn ; extra == 'extras'
Provides-Extra: test
Requires-Dist: pytest ==6.2.5 ; extra == 'test'
Requires-Dist: pytest-automation ==1.1.2 ; extra == 'test'
Requires-Dist: pytest-xdist ==2.4.0 ; extra == 'test'
